coverage_space-1.0.2.post1.dist-info/METADATA
coverage_space-1.0.2.post1.dist-info/RECORD
coverage_space-1.0.2.post1.dist-info/WHEEL
coverage_space-1.0.2.post1.dist-info/entry_points.txt
coverage_space-1.0.2.post1.dist-info/top_level.txt
coveragespace/__init__.py
coveragespace/cache.py
coveragespace/cli.py
coveragespace/client.py
coveragespace/plugins.py
coveragespace/services.py
coveragespace/tests/__init__.py
coveragespace/tests/conftest.py
coveragespace/tests/test_cache.py
coveragespace/tests/test_cli.py
coveragespace/tests/test_plugins.py
coveragespace/tests/test_services.py
tests/__init__.py
tests/conftest.py
tests/test_cli.py
