Metadata-Version: 2.1
Name: coverage-space
Version: 1.0.2.post1
Summary: A place to track your code coverage metrics.
Home-page: https://github.com/jacebrowning/coverage-space-cli
Author: Jace Browning
Author-email: jacebrowning@gmail.com
License: MIT
Platform: UNKNOWN
Classifier: Development Status :: 5 - Production/Stable
Classifier: Environment :: Console
Classifier: Intended Audience :: Developers
Classifier: License :: OSI Approved :: MIT License
Classifier: Natural Language :: English
Classifier: Operating System :: OS Independent
Classifier: Programming Language :: Python
Classifier: Programming Language :: Python :: 2
Classifier: Programming Language :: Python :: 2.7
Classifier: Programming Language :: Python :: 3
Classifier: Programming Language :: Python :: 3.3
Classifier: Programming Language :: Python :: 3.4
Classifier: Programming Language :: Python :: 3.5
Classifier: Programming Language :: Python :: 3.6
Classifier: Topic :: Software Development
Classifier: Topic :: Software Development :: Quality Assurance
Classifier: Topic :: Software Development :: Testing
Requires-Dist: six
Requires-Dist: backports.shutil-get-terminal-size (~=1.0)
Requires-Dist: colorama (~=0.3)
Requires-Dist: coverage
Requires-Dist: docopt (~=0.6)
Requires-Dist: requests (>=2.0)
